<?xml version="1.0" encoding="UTF-8"?>
<mxGraphModel dx="1106" dy="1005" grid="1" gridSize="10" guides="1" tooltips="1" connect="1" arrows="1" fold="1" page="1" pageScale="1" pageWidth="827" pageHeight="1169" math="0" shadow="0">
 <root>
 <mxCell id="0"/>
  <mxCell id="1" parent="0"/>
  <mxCell id= "18" value= "Use the data in other tools." style= "ellipse;whiteSpace=wrap;" vertex="1" parent="1" >
 <mxGeometry x="560" y="480" width="100" height="100" as="geometry"/>
 </mxCell>
  <mxCell id= "19" value= "Share data that i have found with others." style= "ellipse;whiteSpace=wrap;" vertex="1" parent="1" >
 <mxGeometry x="560" y="480" width="100" height="100" as="geometry"/>
 </mxCell>
  <mxCell id= "20" value= "Find the datasets i'm interested in." style= "ellipse;whiteSpace=wrap;" vertex="1" parent="1" >
 <mxGeometry x="560" y="480" width="100" height="100" as="geometry"/>
 </mxCell>
  <mxCell id= "200" value= "Multiple Dimension" style= "shape=partialRectangle;whiteSpace=wrap;left=0;right=0;" vertex="1" parent="1" >
 <mxGeometry x="560" y="480" width="100" height="100" as="geometry"/>
 </mxCell>
  <mxCell id= "201" value= "Datum" style= "shape=partialRectangle;whiteSpace=wrap;left=0;right=0;" vertex="1" parent="1" >
 <mxGeometry x="560" y="480" width="100" height="100" as="geometry"/>
 </mxCell>
  <mxCell id= "202" value= "Multiple Measure" style= "shape=partialRectangle;whiteSpace=wrap;left=0;right=0;" vertex="1" parent="1" >
 <mxGeometry x="560" y="480" width="100" height="100" as="geometry"/>
 </mxCell>
  <mxCell id= "203" value= "Visualisation" style= "shape=partialRectangle;whiteSpace=wrap;left=0;right=0;" vertex="1" parent="1" >
 <mxGeometry x="560" y="480" width="100" height="100" as="geometry"/>
 </mxCell>
  <mxCell id= "204" value= "Currency" style= "shape=partialRectangle;whiteSpace=wrap;left=0;right=0;" vertex="1" parent="1" >
 <mxGeometry x="560" y="480" width="100" height="100" as="geometry"/>
 </mxCell>
  <mxCell id= "205" value= "Monetary Measure" style= "shape=partialRectangle;whiteSpace=wrap;left=0;right=0;" vertex="1" parent="1" >
 <mxGeometry x="560" y="480" width="100" height="100" as="geometry"/>
 </mxCell>
  <mxCell id= "206" value= "Embed Visualisation" style= "shape=partialRectangle;whiteSpace=wrap;left=0;right=0;" vertex="1" parent="1" >
 <mxGeometry x="560" y="480" width="100" height="100" as="geometry"/>
 </mxCell>
  <mxCell id= "207" value= "Textual Description" style= "shape=partialRectangle;whiteSpace=wrap;left=0;right=0;" vertex="1" parent="1" >
 <mxGeometry x="560" y="480" width="100" height="100" as="geometry"/>
 </mxCell>
  <mxCell id= "208" value= "View State" style= "shape=partialRectangle;whiteSpace=wrap;left=0;right=0;" vertex="1" parent="1" >
 <mxGeometry x="560" y="480" width="100" height="100" as="geometry"/>
 </mxCell>
  <mxCell id= "209" value= "Social Network" style= "shape=partialRectangle;whiteSpace=wrap;left=0;right=0;" vertex="1" parent="1" >
 <mxGeometry x="560" y="480" width="100" height="100" as="geometry"/>
 </mxCell>
  <mxCell id= "210" value= "Url" style= "shape=partialRectangle;whiteSpace=wrap;left=0;right=0;" vertex="1" parent="1" >
 <mxGeometry x="560" y="480" width="100" height="100" as="geometry"/>
 </mxCell>
  <mxCell id= "211" value= "Colour" style= "shape=partialRectangle;whiteSpace=wrap;left=0;right=0;" vertex="1" parent="1" >
 <mxGeometry x="560" y="480" width="100" height="100" as="geometry"/>
 </mxCell>
  <mxCell id= "212" value= "Accessible" style= "shape=partialRectangle;whiteSpace=wrap;left=0;right=0;" vertex="1" parent="1" >
 <mxGeometry x="560" y="480" width="100" height="100" as="geometry"/>
 </mxCell>
  <mxCell id= "213" value= "Title" style= "shape=partialRectangle;whiteSpace=wrap;left=0;right=0;" vertex="1" parent="1" >
 <mxGeometry x="560" y="480" width="100" height="100" as="geometry"/>
 </mxCell>
  <mxCell id= "214" value= "Metadata" style= "shape=partialRectangle;whiteSpace=wrap;left=0;right=0;" vertex="1" parent="1" >
 <mxGeometry x="560" y="480" width="100" height="100" as="geometry"/>
 </mxCell>
  <mxCell id= "215" value= "Dataset" style= "shape=partialRectangle;whiteSpace=wrap;left=0;right=0;" vertex="1" parent="1" >
 <mxGeometry x="560" y="480" width="100" height="100" as="geometry"/>
 </mxCell>
  <mxCell id= "216" value= "Bubble Tree" style= "shape=partialRectangle;whiteSpace=wrap;left=0;right=0;" vertex="1" parent="1" >
 <mxGeometry x="560" y="480" width="100" height="100" as="geometry"/>
 </mxCell>
  <mxCell id= "217" value= "Default" style= "shape=partialRectangle;whiteSpace=wrap;left=0;right=0;" vertex="1" parent="1" >
 <mxGeometry x="560" y="480" width="100" height="100" as="geometry"/>
 </mxCell>
  <mxCell id= "218" value= "Treemap" style= "shape=partialRectangle;whiteSpace=wrap;left=0;right=0;" vertex="1" parent="1" >
 <mxGeometry x="560" y="480" width="100" height="100" as="geometry"/>
 </mxCell>
  <mxCell id= "219" value= "Multiple Year" style= "shape=partialRectangle;whiteSpace=wrap;left=0;right=0;" vertex="1" parent="1" >
 <mxGeometry x="560" y="480" width="100" height="100" as="geometry"/>
 </mxCell>
  <mxCell id= "220" value= "Recent Year" style= "shape=partialRectangle;whiteSpace=wrap;left=0;right=0;" vertex="1" parent="1" >
 <mxGeometry x="560" y="480" width="100" height="100" as="geometry"/>
 </mxCell>
  <mxCell id= "221" value= "Pivot Table" style= "shape=partialRectangle;whiteSpace=wrap;left=0;right=0;" vertex="1" parent="1" >
 <mxGeometry x="560" y="480" width="100" height="100" as="geometry"/>
 </mxCell>
  <mxCell id= "222" value= "Map" style= "shape=partialRectangle;whiteSpace=wrap;left=0;right=0;" vertex="1" parent="1" >
 <mxGeometry x="560" y="480" width="100" height="100" as="geometry"/>
 </mxCell>
  <mxCell id= "223" value= "Datum , Consume User" style= "rounded=0;whiteSpace=wrap;" vertex="1" parent="1" >
 <mxGeometry x="560" y="480" width="100" height="100" as="geometry"/>
 </mxCell>
  <mxCell id= "224" value= "Sort Filter Data By Multiple Dimensions" style= "ellipse;whiteSpace=wrap;" vertex="1" parent="1" >
 <mxGeometry x="560" y="480" width="100" height="100" as="geometry"/>
 </mxCell>
  <mxCell id= "225" value= "Sort Aggregate Data By Multiple Measures" style= "ellipse;whiteSpace=wrap;" vertex="1" parent="1" >
 <mxGeometry x="560" y="480" width="100" height="100" as="geometry"/>
 </mxCell>
  <mxCell id= "226" value= "Download A Csv Of The Data Used In Any Visualisation" style= "ellipse;whiteSpace=wrap;" vertex="1" parent="1" >
 <mxGeometry x="560" y="480" width="100" height="100" as="geometry"/>
 </mxCell>
  <mxCell id= "227" value= "Change The Display Of All Monetary Measures Across A Set Of Currencies" style= "ellipse;whiteSpace=wrap;" vertex="1" parent="1" >
 <mxGeometry x="560" y="480" width="100" height="100" as="geometry"/>
 </mxCell>
  <mxCell id= "228" value= "See Textual Descriptions Accompany Embedded Visualisations" style= "ellipse;whiteSpace=wrap;" vertex="1" parent="1" >
 <mxGeometry x="560" y="480" width="100" height="100" as="geometry"/>
 </mxCell>
  <mxCell id= "229" value= "Share A View State As A Url To Social Networks" style= "ellipse;whiteSpace=wrap;" vertex="1" parent="1" >
 <mxGeometry x="560" y="480" width="100" height="100" as="geometry"/>
 </mxCell>
  <mxCell id= "230" value= "Download An Image, Ofa, Particular View State" style= "ellipse;whiteSpace=wrap;" vertex="1" parent="1" >
 <mxGeometry x="560" y="480" width="100" height="100" as="geometry"/>
 </mxCell>
  <mxCell id= "231" value= "Share An Image Of A Particular View State To The Social Networks Support This" style= "ellipse;whiteSpace=wrap;" vertex="1" parent="1" >
 <mxGeometry x="560" y="480" width="100" height="100" as="geometry"/>
 </mxCell>
  <mxCell id= "232" value= "Stepped" style= "ellipse;whiteSpace=wrap;" vertex="1" parent="1" >
 <mxGeometry x="560" y="480" width="100" height="100" as="geometry"/>
 </mxCell>
  <mxCell id= "233" value= "Have Consistent Use Of Colour On Map Visualisations" style= "ellipse;whiteSpace=wrap;" vertex="1" parent="1" >
 <mxGeometry x="560" y="480" width="100" height="100" as="geometry"/>
 </mxCell>
  <mxCell id= "234" value= "Search Any Dataset" style= "ellipse;whiteSpace=wrap;" vertex="1" parent="1" >
 <mxGeometry x="560" y="480" width="100" height="100" as="geometry"/>
 </mxCell>
  <mxCell id= "235" value= "Search Publicly Accessible By Title" style= "ellipse;whiteSpace=wrap;" vertex="1" parent="1" >
 <mxGeometry x="560" y="480" width="100" height="100" as="geometry"/>
 </mxCell>
  <mxCell id= "236" value= "Search Publicly Accessible By Metadata" style= "ellipse;whiteSpace=wrap;" vertex="1" parent="1" >
 <mxGeometry x="560" y="480" width="100" height="100" as="geometry"/>
 </mxCell>
  <mxCell id= "237" value= "Visualize By Default In Bubble Tree" style= "ellipse;whiteSpace=wrap;" vertex="1" parent="1" >
 <mxGeometry x="560" y="480" width="100" height="100" as="geometry"/>
 </mxCell>
  <mxCell id= "238" value= "Visualize By Default In Treemap" style= "ellipse;whiteSpace=wrap;" vertex="1" parent="1" >
 <mxGeometry x="560" y="480" width="100" height="100" as="geometry"/>
 </mxCell>
  <mxCell id= "239" value= "Visualize By Default In Pivot Table" style= "ellipse;whiteSpace=wrap;" vertex="1" parent="1" >
 <mxGeometry x="560" y="480" width="100" height="100" as="geometry"/>
 </mxCell>
  <mxCell id= "240" value= "Visualize By Default In Treemap The Most Recent Year Dataset When Contain Multiple Years" style= "ellipse;whiteSpace=wrap;" vertex="1" parent="1" >
 <mxGeometry x="560" y="480" width="100" height="100" as="geometry"/>
 </mxCell>
  <mxCell id= "242" value= "" style= "endArrow=classic;whiteSpace=wrap;" source= "223" target= "224" edge="1" parent="1" >
<mxGeometry width="50" height="50" as="geometry">
 <mxPoint x="210" y="490" as="sourcePoint"/>
 <mxPoint x="450" y="410" as="targetPoint"/>
 </mxGeometry>
 </mxCell>
  <mxCell id= "243" value= "" style= "endArrow=classic;whiteSpace=wrap;" source= "223" target= "226" edge="1" parent="1" >
<mxGeometry width="50" height="50" as="geometry">
 <mxPoint x="210" y="490" as="sourcePoint"/>
 <mxPoint x="450" y="410" as="targetPoint"/>
 </mxGeometry>
 </mxCell>
  <mxCell id= "244" value= "" style= "endArrow=classic;whiteSpace=wrap;" source= "223" target= "227" edge="1" parent="1" >
<mxGeometry width="50" height="50" as="geometry">
 <mxPoint x="210" y="490" as="sourcePoint"/>
 <mxPoint x="450" y="410" as="targetPoint"/>
 </mxGeometry>
 </mxCell>
  <mxCell id= "245" value= "" style= "endArrow=classic;whiteSpace=wrap;" source= "223" target= "228" edge="1" parent="1" >
<mxGeometry width="50" height="50" as="geometry">
 <mxPoint x="210" y="490" as="sourcePoint"/>
 <mxPoint x="450" y="410" as="targetPoint"/>
 </mxGeometry>
 </mxCell>
  <mxCell id= "246" value= "" style= "endArrow=classic;whiteSpace=wrap;" source= "223" target= "229" edge="1" parent="1" >
<mxGeometry width="50" height="50" as="geometry">
 <mxPoint x="210" y="490" as="sourcePoint"/>
 <mxPoint x="450" y="410" as="targetPoint"/>
 </mxGeometry>
 </mxCell>
  <mxCell id= "247" value= "" style= "endArrow=classic;whiteSpace=wrap;" source= "223" target= "230" edge="1" parent="1" >
<mxGeometry width="50" height="50" as="geometry">
 <mxPoint x="210" y="490" as="sourcePoint"/>
 <mxPoint x="450" y="410" as="targetPoint"/>
 </mxGeometry>
 </mxCell>
  <mxCell id= "248" value= "" style= "endArrow=classic;whiteSpace=wrap;" source= "223" target= "231" edge="1" parent="1" >
<mxGeometry width="50" height="50" as="geometry">
 <mxPoint x="210" y="490" as="sourcePoint"/>
 <mxPoint x="450" y="410" as="targetPoint"/>
 </mxGeometry>
 </mxCell>
  <mxCell id= "249" value= "" style= "endArrow=classic;whiteSpace=wrap;" source= "223" target= "233" edge="1" parent="1" >
<mxGeometry width="50" height="50" as="geometry">
 <mxPoint x="210" y="490" as="sourcePoint"/>
 <mxPoint x="450" y="410" as="targetPoint"/>
 </mxGeometry>
 </mxCell>
  <mxCell id= "250" value= "" style= "endArrow=classic;whiteSpace=wrap;" source= "223" target= "234" edge="1" parent="1" >
<mxGeometry width="50" height="50" as="geometry">
 <mxPoint x="210" y="490" as="sourcePoint"/>
 <mxPoint x="450" y="410" as="targetPoint"/>
 </mxGeometry>
 </mxCell>
  <mxCell id= "251" value= "" style= "endArrow=classic;whiteSpace=wrap;" source= "223" target= "235" edge="1" parent="1" >
<mxGeometry width="50" height="50" as="geometry">
 <mxPoint x="210" y="490" as="sourcePoint"/>
 <mxPoint x="450" y="410" as="targetPoint"/>
 </mxGeometry>
 </mxCell>
  <mxCell id= "252" value= "" style= "endArrow=classic;whiteSpace=wrap;" source= "223" target= "236" edge="1" parent="1" >
<mxGeometry width="50" height="50" as="geometry">
 <mxPoint x="210" y="490" as="sourcePoint"/>
 <mxPoint x="450" y="410" as="targetPoint"/>
 </mxGeometry>
 </mxCell>
  <mxCell id= "253" value= "" style= "endArrow=classic;whiteSpace=wrap;" source= "223" target= "237" edge="1" parent="1" >
<mxGeometry width="50" height="50" as="geometry">
 <mxPoint x="210" y="490" as="sourcePoint"/>
 <mxPoint x="450" y="410" as="targetPoint"/>
 </mxGeometry>
 </mxCell>
  <mxCell id= "254" value= "" style= "endArrow=classic;whiteSpace=wrap;" source= "223" target= "238" edge="1" parent="1" >
<mxGeometry width="50" height="50" as="geometry">
 <mxPoint x="210" y="490" as="sourcePoint"/>
 <mxPoint x="450" y="410" as="targetPoint"/>
 </mxGeometry>
 </mxCell>
  <mxCell id= "255" value= "" style= "endArrow=classic;whiteSpace=wrap;" source= "223" target= "239" edge="1" parent="1" >
<mxGeometry width="50" height="50" as="geometry">
 <mxPoint x="210" y="490" as="sourcePoint"/>
 <mxPoint x="450" y="410" as="targetPoint"/>
 </mxGeometry>
 </mxCell>
  <mxCell id= "256" value= "" style= "endArrow=classic;whiteSpace=wrap;" source= "223" target= "240" edge="1" parent="1" >
<mxGeometry width="50" height="50" as="geometry">
 <mxPoint x="210" y="490" as="sourcePoint"/>
 <mxPoint x="450" y="410" as="targetPoint"/>
 </mxGeometry>
 </mxCell>
  <mxCell id= "257" value= "Datum" style= "endArrow=classic;whiteSpace=wrap;" source= "224" target= "201" edge="1" parent="1" >
<mxGeometry width="50" height="50" as="geometry">
 <mxPoint x="210" y="490" as="sourcePoint"/>
 <mxPoint x="450" y="410" as="targetPoint"/>
 </mxGeometry>
 </mxCell>
  <mxCell id= "258" value= "Multiple Dimension" style= "endArrow=classic;whiteSpace=wrap;" source= "224" target= "200" edge="1" parent="1" >
<mxGeometry width="50" height="50" as="geometry">
 <mxPoint x="210" y="490" as="sourcePoint"/>
 <mxPoint x="450" y="410" as="targetPoint"/>
 </mxGeometry>
 </mxCell>
  <mxCell id= "259" value= "Multiple Measure" style= "endArrow=classic;whiteSpace=wrap;" source= "224" target= "202" edge="1" parent="1" >
<mxGeometry width="50" height="50" as="geometry">
 <mxPoint x="210" y="490" as="sourcePoint"/>
 <mxPoint x="450" y="410" as="targetPoint"/>
 </mxGeometry>
 </mxCell>
  <mxCell id= "260" value= "Multiple Dimension" style= "endArrow=classic;whiteSpace=wrap;" source= "225" target= "200" edge="1" parent="1" >
<mxGeometry width="50" height="50" as="geometry">
 <mxPoint x="210" y="490" as="sourcePoint"/>
 <mxPoint x="450" y="410" as="targetPoint"/>
 </mxGeometry>
 </mxCell>
  <mxCell id= "261" value= "Multiple Measure" style= "endArrow=classic;whiteSpace=wrap;" source= "225" target= "202" edge="1" parent="1" >
<mxGeometry width="50" height="50" as="geometry">
 <mxPoint x="210" y="490" as="sourcePoint"/>
 <mxPoint x="450" y="410" as="targetPoint"/>
 </mxGeometry>
 </mxCell>
  <mxCell id= "262" value= "Datum" style= "endArrow=classic;whiteSpace=wrap;" source= "225" target= "201" edge="1" parent="1" >
<mxGeometry width="50" height="50" as="geometry">
 <mxPoint x="210" y="490" as="sourcePoint"/>
 <mxPoint x="450" y="410" as="targetPoint"/>
 </mxGeometry>
 </mxCell>
  <mxCell id= "263" value= "Visualisation" style= "endArrow=classic;whiteSpace=wrap;" source= "226" target= "203" edge="1" parent="1" >
<mxGeometry width="50" height="50" as="geometry">
 <mxPoint x="210" y="490" as="sourcePoint"/>
 <mxPoint x="450" y="410" as="targetPoint"/>
 </mxGeometry>
 </mxCell>
  <mxCell id= "264" value= "Datum" style= "endArrow=classic;whiteSpace=wrap;" source= "226" target= "201" edge="1" parent="1" >
<mxGeometry width="50" height="50" as="geometry">
 <mxPoint x="210" y="490" as="sourcePoint"/>
 <mxPoint x="450" y="410" as="targetPoint"/>
 </mxGeometry>
 </mxCell>
  <mxCell id= "265" value= "Monetary Measure" style= "endArrow=classic;whiteSpace=wrap;" source= "227" target= "205" edge="1" parent="1" >
<mxGeometry width="50" height="50" as="geometry">
 <mxPoint x="210" y="490" as="sourcePoint"/>
 <mxPoint x="450" y="410" as="targetPoint"/>
 </mxGeometry>
 </mxCell>
  <mxCell id= "266" value= "Currency" style= "endArrow=classic;whiteSpace=wrap;" source= "227" target= "204" edge="1" parent="1" >
<mxGeometry width="50" height="50" as="geometry">
 <mxPoint x="210" y="490" as="sourcePoint"/>
 <mxPoint x="450" y="410" as="targetPoint"/>
 </mxGeometry>
 </mxCell>
  <mxCell id= "267" value= "Textual Description" style= "endArrow=classic;whiteSpace=wrap;" source= "228" target= "207" edge="1" parent="1" >
<mxGeometry width="50" height="50" as="geometry">
 <mxPoint x="210" y="490" as="sourcePoint"/>
 <mxPoint x="450" y="410" as="targetPoint"/>
 </mxGeometry>
 </mxCell>
  <mxCell id= "268" value= "Embed Visualisation" style= "endArrow=classic;whiteSpace=wrap;" source= "228" target= "206" edge="1" parent="1" >
<mxGeometry width="50" height="50" as="geometry">
 <mxPoint x="210" y="490" as="sourcePoint"/>
 <mxPoint x="450" y="410" as="targetPoint"/>
 </mxGeometry>
 </mxCell>
  <mxCell id= "269" value= "View State" style= "endArrow=classic;whiteSpace=wrap;" source= "229" target= "208" edge="1" parent="1" >
<mxGeometry width="50" height="50" as="geometry">
 <mxPoint x="210" y="490" as="sourcePoint"/>
 <mxPoint x="450" y="410" as="targetPoint"/>
 </mxGeometry>
 </mxCell>
  <mxCell id= "270" value= "Url" style= "endArrow=classic;whiteSpace=wrap;" source= "229" target= "210" edge="1" parent="1" >
<mxGeometry width="50" height="50" as="geometry">
 <mxPoint x="210" y="490" as="sourcePoint"/>
 <mxPoint x="450" y="410" as="targetPoint"/>
 </mxGeometry>
 </mxCell>
  <mxCell id= "271" value= "Social Network" style= "endArrow=classic;whiteSpace=wrap;" source= "229" target= "209" edge="1" parent="1" >
<mxGeometry width="50" height="50" as="geometry">
 <mxPoint x="210" y="490" as="sourcePoint"/>
 <mxPoint x="450" y="410" as="targetPoint"/>
 </mxGeometry>
 </mxCell>
  <mxCell id= "272" value= "View State" style= "endArrow=classic;whiteSpace=wrap;" source= "230" target= "208" edge="1" parent="1" >
<mxGeometry width="50" height="50" as="geometry">
 <mxPoint x="210" y="490" as="sourcePoint"/>
 <mxPoint x="450" y="410" as="targetPoint"/>
 </mxGeometry>
 </mxCell>
  <mxCell id= "273" value= "View State" style= "endArrow=classic;whiteSpace=wrap;" source= "231" target= "208" edge="1" parent="1" >
<mxGeometry width="50" height="50" as="geometry">
 <mxPoint x="210" y="490" as="sourcePoint"/>
 <mxPoint x="450" y="410" as="targetPoint"/>
 </mxGeometry>
 </mxCell>
  <mxCell id= "274" value= "Social Network" style= "endArrow=classic;whiteSpace=wrap;" source= "231" target= "209" edge="1" parent="1" >
<mxGeometry width="50" height="50" as="geometry">
 <mxPoint x="210" y="490" as="sourcePoint"/>
 <mxPoint x="450" y="410" as="targetPoint"/>
 </mxGeometry>
 </mxCell>
  <mxCell id= "275" value= "Colour" style= "endArrow=classic;whiteSpace=wrap;" source= "233" target= "211" edge="1" parent="1" >
<mxGeometry width="50" height="50" as="geometry">
 <mxPoint x="210" y="490" as="sourcePoint"/>
 <mxPoint x="450" y="410" as="targetPoint"/>
 </mxGeometry>
 </mxCell>
  <mxCell id= "276" value= "Visualisation" style= "endArrow=classic;whiteSpace=wrap;" source= "233" target= "203" edge="1" parent="1" >
<mxGeometry width="50" height="50" as="geometry">
 <mxPoint x="210" y="490" as="sourcePoint"/>
 <mxPoint x="450" y="410" as="targetPoint"/>
 </mxGeometry>
 </mxCell>
  <mxCell id= "277" value= "Dataset" style= "endArrow=classic;whiteSpace=wrap;" source= "234" target= "215" edge="1" parent="1" >
<mxGeometry width="50" height="50" as="geometry">
 <mxPoint x="210" y="490" as="sourcePoint"/>
 <mxPoint x="450" y="410" as="targetPoint"/>
 </mxGeometry>
 </mxCell>
  <mxCell id= "278" value= "Accessible" style= "endArrow=classic;whiteSpace=wrap;" source= "235" target= "212" edge="1" parent="1" >
<mxGeometry width="50" height="50" as="geometry">
 <mxPoint x="210" y="490" as="sourcePoint"/>
 <mxPoint x="450" y="410" as="targetPoint"/>
 </mxGeometry>
 </mxCell>
  <mxCell id= "279" value= "Title" style= "endArrow=classic;whiteSpace=wrap;" source= "235" target= "213" edge="1" parent="1" >
<mxGeometry width="50" height="50" as="geometry">
 <mxPoint x="210" y="490" as="sourcePoint"/>
 <mxPoint x="450" y="410" as="targetPoint"/>
 </mxGeometry>
 </mxCell>
  <mxCell id= "280" value= "Metadata" style= "endArrow=classic;whiteSpace=wrap;" source= "236" target= "214" edge="1" parent="1" >
<mxGeometry width="50" height="50" as="geometry">
 <mxPoint x="210" y="490" as="sourcePoint"/>
 <mxPoint x="450" y="410" as="targetPoint"/>
 </mxGeometry>
 </mxCell>
  <mxCell id= "281" value= "Accessible" style= "endArrow=classic;whiteSpace=wrap;" source= "236" target= "212" edge="1" parent="1" >
<mxGeometry width="50" height="50" as="geometry">
 <mxPoint x="210" y="490" as="sourcePoint"/>
 <mxPoint x="450" y="410" as="targetPoint"/>
 </mxGeometry>
 </mxCell>
  <mxCell id= "282" value= "Bubble Tree" style= "endArrow=classic;whiteSpace=wrap;" source= "237" target= "216" edge="1" parent="1" >
<mxGeometry width="50" height="50" as="geometry">
 <mxPoint x="210" y="490" as="sourcePoint"/>
 <mxPoint x="450" y="410" as="targetPoint"/>
 </mxGeometry>
 </mxCell>
  <mxCell id= "283" value= "Default" style= "endArrow=classic;whiteSpace=wrap;" source= "237" target= "217" edge="1" parent="1" >
<mxGeometry width="50" height="50" as="geometry">
 <mxPoint x="210" y="490" as="sourcePoint"/>
 <mxPoint x="450" y="410" as="targetPoint"/>
 </mxGeometry>
 </mxCell>
  <mxCell id= "284" value= "Default" style= "endArrow=classic;whiteSpace=wrap;" source= "238" target= "217" edge="1" parent="1" >
<mxGeometry width="50" height="50" as="geometry">
 <mxPoint x="210" y="490" as="sourcePoint"/>
 <mxPoint x="450" y="410" as="targetPoint"/>
 </mxGeometry>
 </mxCell>
  <mxCell id= "285" value= "Treemap" style= "endArrow=classic;whiteSpace=wrap;" source= "238" target= "218" edge="1" parent="1" >
<mxGeometry width="50" height="50" as="geometry">
 <mxPoint x="210" y="490" as="sourcePoint"/>
 <mxPoint x="450" y="410" as="targetPoint"/>
 </mxGeometry>
 </mxCell>
  <mxCell id= "286" value= "Pivot Table" style= "endArrow=classic;whiteSpace=wrap;" source= "239" target= "221" edge="1" parent="1" >
<mxGeometry width="50" height="50" as="geometry">
 <mxPoint x="210" y="490" as="sourcePoint"/>
 <mxPoint x="450" y="410" as="targetPoint"/>
 </mxGeometry>
 </mxCell>
  <mxCell id= "287" value= "Default" style= "endArrow=classic;whiteSpace=wrap;" source= "239" target= "217" edge="1" parent="1" >
<mxGeometry width="50" height="50" as="geometry">
 <mxPoint x="210" y="490" as="sourcePoint"/>
 <mxPoint x="450" y="410" as="targetPoint"/>
 </mxGeometry>
 </mxCell>
  <mxCell id= "288" value= "Default" style= "endArrow=classic;whiteSpace=wrap;" source= "240" target= "217" edge="1" parent="1" >
<mxGeometry width="50" height="50" as="geometry">
 <mxPoint x="210" y="490" as="sourcePoint"/>
 <mxPoint x="450" y="410" as="targetPoint"/>
 </mxGeometry>
 </mxCell>
  <mxCell id= "289" value= "Treemap" style= "endArrow=classic;whiteSpace=wrap;" source= "240" target= "218" edge="1" parent="1" >
<mxGeometry width="50" height="50" as="geometry">
 <mxPoint x="210" y="490" as="sourcePoint"/>
 <mxPoint x="450" y="410" as="targetPoint"/>
 </mxGeometry>
 </mxCell>
  <mxCell id= "290" value= "Multiple Year" style= "endArrow=classic;whiteSpace=wrap;" source= "240" target= "219" edge="1" parent="1" >
<mxGeometry width="50" height="50" as="geometry">
 <mxPoint x="210" y="490" as="sourcePoint"/>
 <mxPoint x="450" y="410" as="targetPoint"/>
 </mxGeometry>
 </mxCell>
  <mxCell id= "291" value= "Recent Year" style= "endArrow=classic;whiteSpace=wrap;" source= "240" target= "220" edge="1" parent="1" >
<mxGeometry width="50" height="50" as="geometry">
 <mxPoint x="210" y="490" as="sourcePoint"/>
 <mxPoint x="450" y="410" as="targetPoint"/>
 </mxGeometry>
 </mxCell>
  <mxCell id= "292" value= "Dataset" style= "endArrow=classic;whiteSpace=wrap;" source= "240" target= "215" edge="1" parent="1" >
<mxGeometry width="50" height="50" as="geometry">
 <mxPoint x="210" y="490" as="sourcePoint"/>
 <mxPoint x="450" y="410" as="targetPoint"/>
 </mxGeometry>
 </mxCell>
  <mxCell id= "302" value= "Map" style= "endArrow=classic;whiteSpace=wrap;" source= "233" target= "222" edge="1" parent="1" >
<mxGeometry width="50" height="50" as="geometry">
 <mxPoint x="210" y="490" as="sourcePoint"/>
 <mxPoint x="450" y="410" as="targetPoint"/>
 </mxGeometry>
 </mxCell>
  <mxCell id= "1000" value= "Data consuming user" style= "rounded=0;whiteSpace=wrap;" vertex="1" parent="1" >
 <mxGeometry x="560" y="480" width="100" height="100" as="geometry"/>
 </mxCell>
  <mxCell id= "1001" value= "" style= "endArrow=classic;whiteSpace=wrap;" source= "1000" target= "18" edge="1" parent="1" >
<mxGeometry width="50" height="50" as="geometry">
 <mxPoint x="210" y="490" as="sourcePoint"/>
 <mxPoint x="450" y="410" as="targetPoint"/>
 </mxGeometry>
 </mxCell>
  <mxCell id= "1002" value= "Data" style= "rounded=0;whiteSpace=wrap;" vertex="1" parent="1" >
 <mxGeometry x="560" y="480" width="100" height="100" as="geometry"/>
 </mxCell>
  <mxCell id= "1003" value= "Data" style= "endArrow=classic;whiteSpace=wrap;" source= "18" target= "1002" edge="1" parent="1" >
<mxGeometry width="50" height="50" as="geometry">
 <mxPoint x="210" y="490" as="sourcePoint"/>
 <mxPoint x="450" y="410" as="targetPoint"/>
 </mxGeometry>
 </mxCell>
  <mxCell id= "1004" value= "Data consuming user" style= "rounded=0;whiteSpace=wrap;" vertex="1" parent="1" >
 <mxGeometry x="560" y="480" width="100" height="100" as="geometry"/>
 </mxCell>
  <mxCell id= "1005" value= "" style= "endArrow=classic;whiteSpace=wrap;" source= "1004" target= "19" edge="1" parent="1" >
<mxGeometry width="50" height="50" as="geometry">
 <mxPoint x="210" y="490" as="sourcePoint"/>
 <mxPoint x="450" y="410" as="targetPoint"/>
 </mxGeometry>
 </mxCell>
  <mxCell id= "1006" value= "Data" style= "rounded=0;whiteSpace=wrap;" vertex="1" parent="1" >
 <mxGeometry x="560" y="480" width="100" height="100" as="geometry"/>
 </mxCell>
  <mxCell id= "1007" value= "Data" style= "endArrow=classic;whiteSpace=wrap;" source= "19" target= "1006" edge="1" parent="1" >
<mxGeometry width="50" height="50" as="geometry">
 <mxPoint x="210" y="490" as="sourcePoint"/>
 <mxPoint x="450" y="410" as="targetPoint"/>
 </mxGeometry>
 </mxCell>
  <mxCell id= "1008" value= "Data consuming user" style= "rounded=0;whiteSpace=wrap;" vertex="1" parent="1" >
 <mxGeometry x="560" y="480" width="100" height="100" as="geometry"/>
 </mxCell>
  <mxCell id= "1009" value= "" style= "endArrow=classic;whiteSpace=wrap;" source= "1008" target= "20" edge="1" parent="1" >
<mxGeometry width="50" height="50" as="geometry">
 <mxPoint x="210" y="490" as="sourcePoint"/>
 <mxPoint x="450" y="410" as="targetPoint"/>
 </mxGeometry>
 </mxCell>
  <mxCell id= "1010" value= "Datasets" style= "rounded=0;whiteSpace=wrap;" vertex="1" parent="1" >
 <mxGeometry x="560" y="480" width="100" height="100" as="geometry"/>
 </mxCell>
  <mxCell id= "1011" value= "Datasets" style= "endArrow=classic;whiteSpace=wrap;" source= "20" target= "1010" edge="1" parent="1" >
<mxGeometry width="50" height="50" as="geometry">
 <mxPoint x="210" y="490" as="sourcePoint"/>
 <mxPoint x="450" y="410" as="targetPoint"/>
 </mxGeometry>
 </mxCell>
</root>
</mxGraphModel>
