<?xml version="1.0" encoding="UTF-8"?>
<mxGraphModel dx="1106" dy="1005" grid="1" gridSize="10" guides="1" tooltips="1" connect="1" arrows="1" fold="1" page="1" pageScale="1" pageWidth="827" pageHeight="1169" math="0" shadow="0">
 <root>
 <mxCell id="0"/>
  <mxCell id="1" parent="0"/>
  <mxCell id= "200" value= "Fabs" style= "shape=partialRectangle;whiteSpace=wrap;left=0;right=0;" vertex="1" parent="1" >
 <mxGeometry x="560" y="480" width="100" height="100" as="geometry"/>
 </mxCell>
  <mxCell id= "201" value= "File" style= "shape=partialRectangle;whiteSpace=wrap;left=0;right=0;" vertex="1" parent="1" >
 <mxGeometry x="560" y="480" width="100" height="100" as="geometry"/>
 </mxCell>
  <mxCell id= "202" value= "Usaspende" style= "shape=partialRectangle;whiteSpace=wrap;left=0;right=0;" vertex="1" parent="1" >
 <mxGeometry x="560" y="480" width="100" height="100" as="geometry"/>
 </mxCell>
  <mxCell id= "203" value= "Derivation" style= "shape=partialRectangle;whiteSpace=wrap;left=0;right=0;" vertex="1" parent="1" >
 <mxGeometry x="560" y="480" width="100" height="100" as="geometry"/>
 </mxCell>
  <mxCell id= "204" value= "Publish Button" style= "shape=partialRectangle;whiteSpace=wrap;left=0;right=0;" vertex="1" parent="1" >
 <mxGeometry x="560" y="480" width="100" height="100" as="geometry"/>
 </mxCell>
  <mxCell id= "205" value= "Warning File" style= "shape=partialRectangle;whiteSpace=wrap;left=0;right=0;" vertex="1" parent="1" >
 <mxGeometry x="560" y="480" width="100" height="100" as="geometry"/>
 </mxCell>
  <mxCell id= "206" value= "Error" style= "shape=partialRectangle;whiteSpace=wrap;left=0;right=0;" vertex="1" parent="1" >
 <mxGeometry x="560" y="480" width="100" height="100" as="geometry"/>
 </mxCell>
  <mxCell id= "207" value= "Complete" style= "shape=partialRectangle;whiteSpace=wrap;left=0;right=0;" vertex="1" parent="1" >
 <mxGeometry x="560" y="480" width="100" height="100" as="geometry"/>
 </mxCell>
  <mxCell id= "208" value= "Accurate Datum" style= "shape=partialRectangle;whiteSpace=wrap;left=0;right=0;" vertex="1" parent="1" >
 <mxGeometry x="560" y="480" width="100" height="100" as="geometry"/>
 </mxCell>
  <mxCell id= "209" value= "D" style= "shape=partialRectangle;whiteSpace=wrap;left=0;right=0;" vertex="1" parent="1" >
 <mxGeometry x="560" y="480" width="100" height="100" as="geometry"/>
 </mxCell>
  <mxCell id= "210" value= "C" style= "shape=partialRectangle;whiteSpace=wrap;left=0;right=0;" vertex="1" parent="1" >
 <mxGeometry x="560" y="480" width="100" height="100" as="geometry"/>
 </mxCell>
  <mxCell id= "211" value= "Record" style= "shape=partialRectangle;whiteSpace=wrap;left=0;right=0;" vertex="1" parent="1" >
 <mxGeometry x="560" y="480" width="100" height="100" as="geometry"/>
 </mxCell>
  <mxCell id= "212" value= "Dun" style= "shape=partialRectangle;whiteSpace=wrap;left=0;right=0;" vertex="1" parent="1" >
 <mxGeometry x="560" y="480" width="100" height="100" as="geometry"/>
 </mxCell>
  <mxCell id= "213" value= "Sam" style= "shape=partialRectangle;whiteSpace=wrap;left=0;right=0;" vertex="1" parent="1" >
 <mxGeometry x="560" y="480" width="100" height="100" as="geometry"/>
 </mxCell>
  <mxCell id= "214" value= "D File" style= "shape=partialRectangle;whiteSpace=wrap;left=0;right=0;" vertex="1" parent="1" >
 <mxGeometry x="560" y="480" width="100" height="100" as="geometry"/>
 </mxCell>
  <mxCell id= "215" value= "Fpds Datum" style= "shape=partialRectangle;whiteSpace=wrap;left=0;right=0;" vertex="1" parent="1" >
 <mxGeometry x="560" y="480" width="100" height="100" as="geometry"/>
 </mxCell>
  <mxCell id= "216" value= "User" style= "shape=partialRectangle;whiteSpace=wrap;left=0;right=0;" vertex="1" parent="1" >
 <mxGeometry x="560" y="480" width="100" height="100" as="geometry"/>
 </mxCell>
  <mxCell id= "217" value= "Case" style= "shape=partialRectangle;whiteSpace=wrap;left=0;right=0;" vertex="1" parent="1" >
 <mxGeometry x="560" y="480" width="100" height="100" as="geometry"/>
 </mxCell>
  <mxCell id= "218" value= "Contract" style= "shape=partialRectangle;whiteSpace=wrap;left=0;right=0;" vertex="1" parent="1" >
 <mxGeometry x="560" y="480" width="100" height="100" as="geometry"/>
 </mxCell>
  <mxCell id= "219" value= "Row" style= "shape=partialRectangle;whiteSpace=wrap;left=0;right=0;" vertex="1" parent="1" >
 <mxGeometry x="560" y="480" width="100" height="100" as="geometry"/>
 </mxCell>
  <mxCell id= "220" value= "Information" style= "shape=partialRectangle;whiteSpace=wrap;left=0;right=0;" vertex="1" parent="1" >
 <mxGeometry x="560" y="480" width="100" height="100" as="geometry"/>
 </mxCell>
  <mxCell id= "221" value= "Registration Date" style= "shape=partialRectangle;whiteSpace=wrap;left=0;right=0;" vertex="1" parent="1" >
 <mxGeometry x="560" y="480" width="100" height="100" as="geometry"/>
 </mxCell>
  <mxCell id= "222" value= "Fabs Submission" style= "shape=partialRectangle;whiteSpace=wrap;left=0;right=0;" vertex="1" parent="1" >
 <mxGeometry x="560" y="480" width="100" height="100" as="geometry"/>
 </mxCell>
  <mxCell id= "223" value= "Nasa Grant" style= "shape=partialRectangle;whiteSpace=wrap;left=0;right=0;" vertex="1" parent="1" >
 <mxGeometry x="560" y="480" width="100" height="100" as="geometry"/>
 </mxCell>
  <mxCell id= "224" value= "Submission" style= "shape=partialRectangle;whiteSpace=wrap;left=0;right=0;" vertex="1" parent="1" >
 <mxGeometry x="560" y="480" width="100" height="100" as="geometry"/>
 </mxCell>
  <mxCell id= "225" value= "Cfda" style= "shape=partialRectangle;whiteSpace=wrap;left=0;right=0;" vertex="1" parent="1" >
 <mxGeometry x="560" y="480" width="100" height="100" as="geometry"/>
 </mxCell>
  <mxCell id= "226" value= "User" style= "rounded=0;whiteSpace=wrap;" vertex="1" parent="1" >
 <mxGeometry x="560" y="480" width="100" height="100" as="geometry"/>
 </mxCell>
  <mxCell id= "227" value= "-pron-" style= "rounded=0;whiteSpace=wrap;" vertex="1" parent="1" >
 <mxGeometry x="560" y="480" width="100" height="100" as="geometry"/>
 </mxCell>
  <mxCell id= "228" value= "actorwhose" style= "rounded=0;whiteSpace=wrap;" vertex="1" parent="1" >
 <mxGeometry x="560" y="480" width="100" height="100" as="geometry"/>
 </mxCell>
  <mxCell id= "229" value= "Developer" style= "rounded=0;whiteSpace=wrap;" vertex="1" parent="1" >
 <mxGeometry x="560" y="480" width="100" height="100" as="geometry"/>
 </mxCell>
  <mxCell id= "230" value= "Publish Files From Fabs Via Usaspending" style= "ellipse;whiteSpace=wrap;" vertex="1" parent="1" >
 <mxGeometry x="560" y="480" width="100" height="100" as="geometry"/>
 </mxCell>
  <mxCell id= "231" value= "Access" style= "ellipse;whiteSpace=wrap;" vertex="1" parent="1" >
 <mxGeometry x="560" y="480" width="100" height="100" as="geometry"/>
 </mxCell>
  <mxCell id= "232" value= "Click The Publish Button In Fabs The Derivations Are Happening" style= "ellipse;whiteSpace=wrap;" vertex="1" parent="1" >
 <mxGeometry x="560" y="480" width="100" height="100" as="geometry"/>
 </mxCell>
  <mxCell id= "233" value= "Deactivate" style= "ellipse;whiteSpace=wrap;" vertex="1" parent="1" >
 <mxGeometry x="560" y="480" width="100" height="100" as="geometry"/>
 </mxCell>
  <mxCell id= "234" value= "Appear In Error" style= "ellipse;whiteSpace=wrap;" vertex="1" parent="1" >
 <mxGeometry x="560" y="480" width="100" height="100" as="geometry"/>
 </mxCell>
  <mxCell id= "235" value= "Appear In The Warning Files" style= "ellipse;whiteSpace=wrap;" vertex="1" parent="1" >
 <mxGeometry x="560" y="480" width="100" height="100" as="geometry"/>
 </mxCell>
  <mxCell id= "236" value= "Have Accurate Data To Ppopcongressionaldistrict" style= "ellipse;whiteSpace=wrap;" vertex="1" parent="1" >
 <mxGeometry x="560" y="480" width="100" height="100" as="geometry"/>
 </mxCell>
  <mxCell id= "237" value= "Have Complete" style= "ellipse;whiteSpace=wrap;" vertex="1" parent="1" >
 <mxGeometry x="560" y="480" width="100" height="100" as="geometry"/>
 </mxCell>
  <mxCell id= "238" value= "Have Accurate Data To Ppopcode" style= "ellipse;whiteSpace=wrap;" vertex="1" parent="1" >
 <mxGeometry x="560" y="480" width="100" height="100" as="geometry"/>
 </mxCell>
  <mxCell id= "239" value= "Accept Records Actiontypes Are C" style= "ellipse;whiteSpace=wrap;" vertex="1" parent="1" >
 <mxGeometry x="560" y="480" width="100" height="100" as="geometry"/>
 </mxCell>
  <mxCell id= "240" value= "Accept Records Actiontypes Are The Duns" style= "ellipse;whiteSpace=wrap;" vertex="1" parent="1" >
 <mxGeometry x="560" y="480" width="100" height="100" as="geometry"/>
 </mxCell>
  <mxCell id= "241" value= "Accept Records Actiontypes Are D" style= "ellipse;whiteSpace=wrap;" vertex="1" parent="1" >
 <mxGeometry x="560" y="480" width="100" height="100" as="geometry"/>
 </mxCell>
  <mxCell id= "242" value= "Accept Records Actiontypes Are B" style= "ellipse;whiteSpace=wrap;" vertex="1" parent="1" >
 <mxGeometry x="560" y="480" width="100" height="100" as="geometry"/>
 </mxCell>
  <mxCell id= "243" value= "After Accept Records Actiondates Are Before The Current Registration Date In Sam The Initial Registration Date" style= "ellipse;whiteSpace=wrap;" vertex="1" parent="1" >
 <mxGeometry x="560" y="480" width="100" height="100" as="geometry"/>
 </mxCell>
  <mxCell id= "244" value= "Generate D Files From Fabs" style= "ellipse;whiteSpace=wrap;" vertex="1" parent="1" >
 <mxGeometry x="560" y="480" width="100" height="100" as="geometry"/>
 </mxCell>
  <mxCell id= "245" value= "Generate D Files From Fpds Datum" style= "ellipse;whiteSpace=wrap;" vertex="1" parent="1" >
 <mxGeometry x="560" y="480" width="100" height="100" as="geometry"/>
 </mxCell>
  <mxCell id= "246" value= "Validate D Files From Fabs" style= "ellipse;whiteSpace=wrap;" vertex="1" parent="1" >
 <mxGeometry x="560" y="480" width="100" height="100" as="geometry"/>
 </mxCell>
  <mxCell id= "247" value= "Validate D Files From Fpds Datum" style= "ellipse;whiteSpace=wrap;" vertex="1" parent="1" >
 <mxGeometry x="560" y="480" width="100" height="100" as="geometry"/>
 </mxCell>
  <mxCell id= "248" value= "Prevent Users From Publishing, Double Fabs Submissions Refreshing" style= "ellipse;whiteSpace=wrap;" vertex="1" parent="1" >
 <mxGeometry x="560" y="480" width="100" height="100" as="geometry"/>
 </mxCell>
  <mxCell id= "249" value= "Clarify To Users" style= "ellipse;whiteSpace=wrap;" vertex="1" parent="1" >
 <mxGeometry x="560" y="480" width="100" height="100" as="geometry"/>
 </mxCell>
  <mxCell id= "250" value= "See" style= "ellipse;whiteSpace=wrap;" vertex="1" parent="1" >
 <mxGeometry x="560" y="480" width="100" height="100" as="geometry"/>
 </mxCell>
  <mxCell id= "251" value= "Publish" style= "ellipse;whiteSpace=wrap;" vertex="1" parent="1" >
 <mxGeometry x="560" y="480" width="100" height="100" as="geometry"/>
 </mxCell>
  <mxCell id= "253" value= "" style= "endArrow=classic;whiteSpace=wrap;" source= "226" target= "230" edge="1" parent="1" >
<mxGeometry width="50" height="50" as="geometry">
 <mxPoint x="210" y="490" as="sourcePoint"/>
 <mxPoint x="450" y="410" as="targetPoint"/>
 </mxGeometry>
 </mxCell>
  <mxCell id= "254" value= "" style= "endArrow=classic;whiteSpace=wrap;" source= "226" target= "231" edge="1" parent="1" >
<mxGeometry width="50" height="50" as="geometry">
 <mxPoint x="210" y="490" as="sourcePoint"/>
 <mxPoint x="450" y="410" as="targetPoint"/>
 </mxGeometry>
 </mxCell>
  <mxCell id= "255" value= "" style= "endArrow=classic;whiteSpace=wrap;" source= "226" target= "232" edge="1" parent="1" >
<mxGeometry width="50" height="50" as="geometry">
 <mxPoint x="210" y="490" as="sourcePoint"/>
 <mxPoint x="450" y="410" as="targetPoint"/>
 </mxGeometry>
 </mxCell>
  <mxCell id= "256" value= "" style= "endArrow=classic;whiteSpace=wrap;" source= "226" target= "233" edge="1" parent="1" >
<mxGeometry width="50" height="50" as="geometry">
 <mxPoint x="210" y="490" as="sourcePoint"/>
 <mxPoint x="450" y="410" as="targetPoint"/>
 </mxGeometry>
 </mxCell>
  <mxCell id= "257" value= "" style= "endArrow=classic;whiteSpace=wrap;" source= "226" target= "234" edge="1" parent="1" >
<mxGeometry width="50" height="50" as="geometry">
 <mxPoint x="210" y="490" as="sourcePoint"/>
 <mxPoint x="450" y="410" as="targetPoint"/>
 </mxGeometry>
 </mxCell>
  <mxCell id= "258" value= "" style= "endArrow=classic;whiteSpace=wrap;" source= "226" target= "235" edge="1" parent="1" >
<mxGeometry width="50" height="50" as="geometry">
 <mxPoint x="210" y="490" as="sourcePoint"/>
 <mxPoint x="450" y="410" as="targetPoint"/>
 </mxGeometry>
 </mxCell>
  <mxCell id= "259" value= "" style= "endArrow=classic;whiteSpace=wrap;" source= "226" target= "236" edge="1" parent="1" >
<mxGeometry width="50" height="50" as="geometry">
 <mxPoint x="210" y="490" as="sourcePoint"/>
 <mxPoint x="450" y="410" as="targetPoint"/>
 </mxGeometry>
 </mxCell>
  <mxCell id= "260" value= "" style= "endArrow=classic;whiteSpace=wrap;" source= "226" target= "237" edge="1" parent="1" >
<mxGeometry width="50" height="50" as="geometry">
 <mxPoint x="210" y="490" as="sourcePoint"/>
 <mxPoint x="450" y="410" as="targetPoint"/>
 </mxGeometry>
 </mxCell>
  <mxCell id= "261" value= "" style= "endArrow=classic;whiteSpace=wrap;" source= "226" target= "238" edge="1" parent="1" >
<mxGeometry width="50" height="50" as="geometry">
 <mxPoint x="210" y="490" as="sourcePoint"/>
 <mxPoint x="450" y="410" as="targetPoint"/>
 </mxGeometry>
 </mxCell>
  <mxCell id= "262" value= "" style= "endArrow=classic;whiteSpace=wrap;" source= "226" target= "239" edge="1" parent="1" >
<mxGeometry width="50" height="50" as="geometry">
 <mxPoint x="210" y="490" as="sourcePoint"/>
 <mxPoint x="450" y="410" as="targetPoint"/>
 </mxGeometry>
 </mxCell>
  <mxCell id= "263" value= "" style= "endArrow=classic;whiteSpace=wrap;" source= "226" target= "240" edge="1" parent="1" >
<mxGeometry width="50" height="50" as="geometry">
 <mxPoint x="210" y="490" as="sourcePoint"/>
 <mxPoint x="450" y="410" as="targetPoint"/>
 </mxGeometry>
 </mxCell>
  <mxCell id= "264" value= "" style= "endArrow=classic;whiteSpace=wrap;" source= "226" target= "241" edge="1" parent="1" >
<mxGeometry width="50" height="50" as="geometry">
 <mxPoint x="210" y="490" as="sourcePoint"/>
 <mxPoint x="450" y="410" as="targetPoint"/>
 </mxGeometry>
 </mxCell>
  <mxCell id= "265" value= "" style= "endArrow=classic;whiteSpace=wrap;" source= "226" target= "242" edge="1" parent="1" >
<mxGeometry width="50" height="50" as="geometry">
 <mxPoint x="210" y="490" as="sourcePoint"/>
 <mxPoint x="450" y="410" as="targetPoint"/>
 </mxGeometry>
 </mxCell>
  <mxCell id= "266" value= "" style= "endArrow=classic;whiteSpace=wrap;" source= "226" target= "243" edge="1" parent="1" >
<mxGeometry width="50" height="50" as="geometry">
 <mxPoint x="210" y="490" as="sourcePoint"/>
 <mxPoint x="450" y="410" as="targetPoint"/>
 </mxGeometry>
 </mxCell>
  <mxCell id= "267" value= "" style= "endArrow=classic;whiteSpace=wrap;" source= "226" target= "244" edge="1" parent="1" >
<mxGeometry width="50" height="50" as="geometry">
 <mxPoint x="210" y="490" as="sourcePoint"/>
 <mxPoint x="450" y="410" as="targetPoint"/>
 </mxGeometry>
 </mxCell>
  <mxCell id= "268" value= "" style= "endArrow=classic;whiteSpace=wrap;" source= "226" target= "245" edge="1" parent="1" >
<mxGeometry width="50" height="50" as="geometry">
 <mxPoint x="210" y="490" as="sourcePoint"/>
 <mxPoint x="450" y="410" as="targetPoint"/>
 </mxGeometry>
 </mxCell>
  <mxCell id= "269" value= "" style= "endArrow=classic;whiteSpace=wrap;" source= "226" target= "246" edge="1" parent="1" >
<mxGeometry width="50" height="50" as="geometry">
 <mxPoint x="210" y="490" as="sourcePoint"/>
 <mxPoint x="450" y="410" as="targetPoint"/>
 </mxGeometry>
 </mxCell>
  <mxCell id= "270" value= "" style= "endArrow=classic;whiteSpace=wrap;" source= "226" target= "247" edge="1" parent="1" >
<mxGeometry width="50" height="50" as="geometry">
 <mxPoint x="210" y="490" as="sourcePoint"/>
 <mxPoint x="450" y="410" as="targetPoint"/>
 </mxGeometry>
 </mxCell>
  <mxCell id= "271" value= "" style= "endArrow=classic;whiteSpace=wrap;" source= "227" target= "234" edge="1" parent="1" >
<mxGeometry width="50" height="50" as="geometry">
 <mxPoint x="210" y="490" as="sourcePoint"/>
 <mxPoint x="450" y="410" as="targetPoint"/>
 </mxGeometry>
 </mxCell>
  <mxCell id= "272" value= "" style= "endArrow=classic;whiteSpace=wrap;" source= "227" target= "235" edge="1" parent="1" >
<mxGeometry width="50" height="50" as="geometry">
 <mxPoint x="210" y="490" as="sourcePoint"/>
 <mxPoint x="450" y="410" as="targetPoint"/>
 </mxGeometry>
 </mxCell>
  <mxCell id= "273" value= "" style= "endArrow=classic;whiteSpace=wrap;" source= "228" target= "239" edge="1" parent="1" >
<mxGeometry width="50" height="50" as="geometry">
 <mxPoint x="210" y="490" as="sourcePoint"/>
 <mxPoint x="450" y="410" as="targetPoint"/>
 </mxGeometry>
 </mxCell>
  <mxCell id= "274" value= "" style= "endArrow=classic;whiteSpace=wrap;" source= "228" target= "240" edge="1" parent="1" >
<mxGeometry width="50" height="50" as="geometry">
 <mxPoint x="210" y="490" as="sourcePoint"/>
 <mxPoint x="450" y="410" as="targetPoint"/>
 </mxGeometry>
 </mxCell>
  <mxCell id= "275" value= "" style= "endArrow=classic;whiteSpace=wrap;" source= "228" target= "241" edge="1" parent="1" >
<mxGeometry width="50" height="50" as="geometry">
 <mxPoint x="210" y="490" as="sourcePoint"/>
 <mxPoint x="450" y="410" as="targetPoint"/>
 </mxGeometry>
 </mxCell>
  <mxCell id= "276" value= "" style= "endArrow=classic;whiteSpace=wrap;" source= "228" target= "242" edge="1" parent="1" >
<mxGeometry width="50" height="50" as="geometry">
 <mxPoint x="210" y="490" as="sourcePoint"/>
 <mxPoint x="450" y="410" as="targetPoint"/>
 </mxGeometry>
 </mxCell>
  <mxCell id= "277" value= "" style= "endArrow=classic;whiteSpace=wrap;" source= "228" target= "243" edge="1" parent="1" >
<mxGeometry width="50" height="50" as="geometry">
 <mxPoint x="210" y="490" as="sourcePoint"/>
 <mxPoint x="450" y="410" as="targetPoint"/>
 </mxGeometry>
 </mxCell>
  <mxCell id= "278" value= "" style= "endArrow=classic;whiteSpace=wrap;" source= "229" target= "248" edge="1" parent="1" >
<mxGeometry width="50" height="50" as="geometry">
 <mxPoint x="210" y="490" as="sourcePoint"/>
 <mxPoint x="450" y="410" as="targetPoint"/>
 </mxGeometry>
 </mxCell>
  <mxCell id= "279" value= "" style= "endArrow=classic;whiteSpace=wrap;" source= "229" target= "249" edge="1" parent="1" >
<mxGeometry width="50" height="50" as="geometry">
 <mxPoint x="210" y="490" as="sourcePoint"/>
 <mxPoint x="450" y="410" as="targetPoint"/>
 </mxGeometry>
 </mxCell>
  <mxCell id= "280" value= "File" style= "endArrow=classic;whiteSpace=wrap;" source= "230" target= "201" edge="1" parent="1" >
<mxGeometry width="50" height="50" as="geometry">
 <mxPoint x="210" y="490" as="sourcePoint"/>
 <mxPoint x="450" y="410" as="targetPoint"/>
 </mxGeometry>
 </mxCell>
  <mxCell id= "281" value= "Fabs" style= "endArrow=classic;whiteSpace=wrap;" source= "230" target= "200" edge="1" parent="1" >
<mxGeometry width="50" height="50" as="geometry">
 <mxPoint x="210" y="490" as="sourcePoint"/>
 <mxPoint x="450" y="410" as="targetPoint"/>
 </mxGeometry>
 </mxCell>
  <mxCell id= "282" value= "Usaspende" style= "endArrow=classic;whiteSpace=wrap;" source= "230" target= "202" edge="1" parent="1" >
<mxGeometry width="50" height="50" as="geometry">
 <mxPoint x="210" y="490" as="sourcePoint"/>
 <mxPoint x="450" y="410" as="targetPoint"/>
 </mxGeometry>
 </mxCell>
  <mxCell id= "283" value= "" style= "endArrow=classic;whiteSpace=wrap;" source= "231" target= "230" edge="1" parent="1" >
<mxGeometry width="50" height="50" as="geometry">
 <mxPoint x="210" y="490" as="sourcePoint"/>
 <mxPoint x="450" y="410" as="targetPoint"/>
 </mxGeometry>
 </mxCell>
  <mxCell id= "284" value= "" style= "endArrow=classic;whiteSpace=wrap;" source= "232" target= "233" edge="1" parent="1" >
<mxGeometry width="50" height="50" as="geometry">
 <mxPoint x="210" y="490" as="sourcePoint"/>
 <mxPoint x="450" y="410" as="targetPoint"/>
 </mxGeometry>
 </mxCell>
  <mxCell id= "285" value= "Publish Button" style= "endArrow=classic;whiteSpace=wrap;" source= "232" target= "204" edge="1" parent="1" >
<mxGeometry width="50" height="50" as="geometry">
 <mxPoint x="210" y="490" as="sourcePoint"/>
 <mxPoint x="450" y="410" as="targetPoint"/>
 </mxGeometry>
 </mxCell>
  <mxCell id= "286" value= "Derivation" style= "endArrow=classic;whiteSpace=wrap;" source= "232" target= "203" edge="1" parent="1" >
<mxGeometry width="50" height="50" as="geometry">
 <mxPoint x="210" y="490" as="sourcePoint"/>
 <mxPoint x="450" y="410" as="targetPoint"/>
 </mxGeometry>
 </mxCell>
  <mxCell id= "287" value= "Fabs" style= "endArrow=classic;whiteSpace=wrap;" source= "232" target= "200" edge="1" parent="1" >
<mxGeometry width="50" height="50" as="geometry">
 <mxPoint x="210" y="490" as="sourcePoint"/>
 <mxPoint x="450" y="410" as="targetPoint"/>
 </mxGeometry>
 </mxCell>
  <mxCell id= "288" value= "Fabs" style= "endArrow=classic;whiteSpace=wrap;" source= "233" target= "200" edge="1" parent="1" >
<mxGeometry width="50" height="50" as="geometry">
 <mxPoint x="210" y="490" as="sourcePoint"/>
 <mxPoint x="450" y="410" as="targetPoint"/>
 </mxGeometry>
 </mxCell>
  <mxCell id= "289" value= "Error" style= "endArrow=classic;whiteSpace=wrap;" source= "234" target= "206" edge="1" parent="1" >
<mxGeometry width="50" height="50" as="geometry">
 <mxPoint x="210" y="490" as="sourcePoint"/>
 <mxPoint x="450" y="410" as="targetPoint"/>
 </mxGeometry>
 </mxCell>
  <mxCell id= "290" value= "File" style= "endArrow=classic;whiteSpace=wrap;" source= "234" target= "201" edge="1" parent="1" >
<mxGeometry width="50" height="50" as="geometry">
 <mxPoint x="210" y="490" as="sourcePoint"/>
 <mxPoint x="450" y="410" as="targetPoint"/>
 </mxGeometry>
 </mxCell>
  <mxCell id= "291" value= "Warning File" style= "endArrow=classic;whiteSpace=wrap;" source= "235" target= "205" edge="1" parent="1" >
<mxGeometry width="50" height="50" as="geometry">
 <mxPoint x="210" y="490" as="sourcePoint"/>
 <mxPoint x="450" y="410" as="targetPoint"/>
 </mxGeometry>
 </mxCell>
  <mxCell id= "292" value= "File" style= "endArrow=classic;whiteSpace=wrap;" source= "235" target= "201" edge="1" parent="1" >
<mxGeometry width="50" height="50" as="geometry">
 <mxPoint x="210" y="490" as="sourcePoint"/>
 <mxPoint x="450" y="410" as="targetPoint"/>
 </mxGeometry>
 </mxCell>
  <mxCell id= "293" value= "Accurate Datum" style= "endArrow=classic;whiteSpace=wrap;" source= "236" target= "208" edge="1" parent="1" >
<mxGeometry width="50" height="50" as="geometry">
 <mxPoint x="210" y="490" as="sourcePoint"/>
 <mxPoint x="450" y="410" as="targetPoint"/>
 </mxGeometry>
 </mxCell>
  <mxCell id= "294" value= "Usaspende" style= "endArrow=classic;whiteSpace=wrap;" source= "236" target= "202" edge="1" parent="1" >
<mxGeometry width="50" height="50" as="geometry">
 <mxPoint x="210" y="490" as="sourcePoint"/>
 <mxPoint x="450" y="410" as="targetPoint"/>
 </mxGeometry>
 </mxCell>
  <mxCell id= "295" value= "Complete" style= "endArrow=classic;whiteSpace=wrap;" source= "237" target= "207" edge="1" parent="1" >
<mxGeometry width="50" height="50" as="geometry">
 <mxPoint x="210" y="490" as="sourcePoint"/>
 <mxPoint x="450" y="410" as="targetPoint"/>
 </mxGeometry>
 </mxCell>
  <mxCell id= "296" value= "Accurate Datum" style= "endArrow=classic;whiteSpace=wrap;" source= "238" target= "208" edge="1" parent="1" >
<mxGeometry width="50" height="50" as="geometry">
 <mxPoint x="210" y="490" as="sourcePoint"/>
 <mxPoint x="450" y="410" as="targetPoint"/>
 </mxGeometry>
 </mxCell>
  <mxCell id= "297" value= "Usaspende" style= "endArrow=classic;whiteSpace=wrap;" source= "238" target= "202" edge="1" parent="1" >
<mxGeometry width="50" height="50" as="geometry">
 <mxPoint x="210" y="490" as="sourcePoint"/>
 <mxPoint x="450" y="410" as="targetPoint"/>
 </mxGeometry>
 </mxCell>
  <mxCell id= "298" value= "C" style= "endArrow=classic;whiteSpace=wrap;" source= "239" target= "210" edge="1" parent="1" >
<mxGeometry width="50" height="50" as="geometry">
 <mxPoint x="210" y="490" as="sourcePoint"/>
 <mxPoint x="450" y="410" as="targetPoint"/>
 </mxGeometry>
 </mxCell>
  <mxCell id= "299" value= "Record" style= "endArrow=classic;whiteSpace=wrap;" source= "239" target= "211" edge="1" parent="1" >
<mxGeometry width="50" height="50" as="geometry">
 <mxPoint x="210" y="490" as="sourcePoint"/>
 <mxPoint x="450" y="410" as="targetPoint"/>
 </mxGeometry>
 </mxCell>
  <mxCell id= "300" value= "Usaspende" style= "endArrow=classic;whiteSpace=wrap;" source= "239" target= "202" edge="1" parent="1" >
<mxGeometry width="50" height="50" as="geometry">
 <mxPoint x="210" y="490" as="sourcePoint"/>
 <mxPoint x="450" y="410" as="targetPoint"/>
 </mxGeometry>
 </mxCell>
  <mxCell id= "301" value= "Dun" style= "endArrow=classic;whiteSpace=wrap;" source= "240" target= "212" edge="1" parent="1" >
<mxGeometry width="50" height="50" as="geometry">
 <mxPoint x="210" y="490" as="sourcePoint"/>
 <mxPoint x="450" y="410" as="targetPoint"/>
 </mxGeometry>
 </mxCell>
  <mxCell id= "302" value= "Record" style= "endArrow=classic;whiteSpace=wrap;" source= "240" target= "211" edge="1" parent="1" >
<mxGeometry width="50" height="50" as="geometry">
 <mxPoint x="210" y="490" as="sourcePoint"/>
 <mxPoint x="450" y="410" as="targetPoint"/>
 </mxGeometry>
 </mxCell>
  <mxCell id= "303" value= "Usaspende" style= "endArrow=classic;whiteSpace=wrap;" source= "240" target= "202" edge="1" parent="1" >
<mxGeometry width="50" height="50" as="geometry">
 <mxPoint x="210" y="490" as="sourcePoint"/>
 <mxPoint x="450" y="410" as="targetPoint"/>
 </mxGeometry>
 </mxCell>
  <mxCell id= "304" value= "D" style= "endArrow=classic;whiteSpace=wrap;" source= "241" target= "209" edge="1" parent="1" >
<mxGeometry width="50" height="50" as="geometry">
 <mxPoint x="210" y="490" as="sourcePoint"/>
 <mxPoint x="450" y="410" as="targetPoint"/>
 </mxGeometry>
 </mxCell>
  <mxCell id= "305" value= "Record" style= "endArrow=classic;whiteSpace=wrap;" source= "241" target= "211" edge="1" parent="1" >
<mxGeometry width="50" height="50" as="geometry">
 <mxPoint x="210" y="490" as="sourcePoint"/>
 <mxPoint x="450" y="410" as="targetPoint"/>
 </mxGeometry>
 </mxCell>
  <mxCell id= "306" value= "Usaspende" style= "endArrow=classic;whiteSpace=wrap;" source= "241" target= "202" edge="1" parent="1" >
<mxGeometry width="50" height="50" as="geometry">
 <mxPoint x="210" y="490" as="sourcePoint"/>
 <mxPoint x="450" y="410" as="targetPoint"/>
 </mxGeometry>
 </mxCell>
  <mxCell id= "307" value= "Record" style= "endArrow=classic;whiteSpace=wrap;" source= "242" target= "211" edge="1" parent="1" >
<mxGeometry width="50" height="50" as="geometry">
 <mxPoint x="210" y="490" as="sourcePoint"/>
 <mxPoint x="450" y="410" as="targetPoint"/>
 </mxGeometry>
 </mxCell>
  <mxCell id= "308" value= "Usaspende" style= "endArrow=classic;whiteSpace=wrap;" source= "242" target= "202" edge="1" parent="1" >
<mxGeometry width="50" height="50" as="geometry">
 <mxPoint x="210" y="490" as="sourcePoint"/>
 <mxPoint x="450" y="410" as="targetPoint"/>
 </mxGeometry>
 </mxCell>
  <mxCell id= "309" value= "Registration Date" style= "endArrow=classic;whiteSpace=wrap;" source= "243" target= "221" edge="1" parent="1" >
<mxGeometry width="50" height="50" as="geometry">
 <mxPoint x="210" y="490" as="sourcePoint"/>
 <mxPoint x="450" y="410" as="targetPoint"/>
 </mxGeometry>
 </mxCell>
  <mxCell id= "310" value= "Record" style= "endArrow=classic;whiteSpace=wrap;" source= "243" target= "211" edge="1" parent="1" >
<mxGeometry width="50" height="50" as="geometry">
 <mxPoint x="210" y="490" as="sourcePoint"/>
 <mxPoint x="450" y="410" as="targetPoint"/>
 </mxGeometry>
 </mxCell>
  <mxCell id= "311" value= "Sam" style= "endArrow=classic;whiteSpace=wrap;" source= "243" target= "213" edge="1" parent="1" >
<mxGeometry width="50" height="50" as="geometry">
 <mxPoint x="210" y="490" as="sourcePoint"/>
 <mxPoint x="450" y="410" as="targetPoint"/>
 </mxGeometry>
 </mxCell>
  <mxCell id= "312" value= "Usaspende" style= "endArrow=classic;whiteSpace=wrap;" source= "243" target= "202" edge="1" parent="1" >
<mxGeometry width="50" height="50" as="geometry">
 <mxPoint x="210" y="490" as="sourcePoint"/>
 <mxPoint x="450" y="410" as="targetPoint"/>
 </mxGeometry>
 </mxCell>
  <mxCell id= "313" value= "D File" style= "endArrow=classic;whiteSpace=wrap;" source= "244" target= "214" edge="1" parent="1" >
<mxGeometry width="50" height="50" as="geometry">
 <mxPoint x="210" y="490" as="sourcePoint"/>
 <mxPoint x="450" y="410" as="targetPoint"/>
 </mxGeometry>
 </mxCell>
  <mxCell id= "314" value= "Fabs" style= "endArrow=classic;whiteSpace=wrap;" source= "244" target= "200" edge="1" parent="1" >
<mxGeometry width="50" height="50" as="geometry">
 <mxPoint x="210" y="490" as="sourcePoint"/>
 <mxPoint x="450" y="410" as="targetPoint"/>
 </mxGeometry>
 </mxCell>
  <mxCell id= "315" value= "Fpds Datum" style= "endArrow=classic;whiteSpace=wrap;" source= "245" target= "215" edge="1" parent="1" >
<mxGeometry width="50" height="50" as="geometry">
 <mxPoint x="210" y="490" as="sourcePoint"/>
 <mxPoint x="450" y="410" as="targetPoint"/>
 </mxGeometry>
 </mxCell>
  <mxCell id= "316" value= "D File" style= "endArrow=classic;whiteSpace=wrap;" source= "245" target= "214" edge="1" parent="1" >
<mxGeometry width="50" height="50" as="geometry">
 <mxPoint x="210" y="490" as="sourcePoint"/>
 <mxPoint x="450" y="410" as="targetPoint"/>
 </mxGeometry>
 </mxCell>
  <mxCell id= "317" value= "Fabs" style= "endArrow=classic;whiteSpace=wrap;" source= "246" target= "200" edge="1" parent="1" >
<mxGeometry width="50" height="50" as="geometry">
 <mxPoint x="210" y="490" as="sourcePoint"/>
 <mxPoint x="450" y="410" as="targetPoint"/>
 </mxGeometry>
 </mxCell>
  <mxCell id= "318" value= "D File" style= "endArrow=classic;whiteSpace=wrap;" source= "246" target= "214" edge="1" parent="1" >
<mxGeometry width="50" height="50" as="geometry">
 <mxPoint x="210" y="490" as="sourcePoint"/>
 <mxPoint x="450" y="410" as="targetPoint"/>
 </mxGeometry>
 </mxCell>
  <mxCell id= "319" value= "D File" style= "endArrow=classic;whiteSpace=wrap;" source= "247" target= "214" edge="1" parent="1" >
<mxGeometry width="50" height="50" as="geometry">
 <mxPoint x="210" y="490" as="sourcePoint"/>
 <mxPoint x="450" y="410" as="targetPoint"/>
 </mxGeometry>
 </mxCell>
  <mxCell id= "320" value= "Fpds Datum" style= "endArrow=classic;whiteSpace=wrap;" source= "247" target= "215" edge="1" parent="1" >
<mxGeometry width="50" height="50" as="geometry">
 <mxPoint x="210" y="490" as="sourcePoint"/>
 <mxPoint x="450" y="410" as="targetPoint"/>
 </mxGeometry>
 </mxCell>
  <mxCell id= "321" value= "User" style= "endArrow=classic;whiteSpace=wrap;" source= "248" target= "216" edge="1" parent="1" >
<mxGeometry width="50" height="50" as="geometry">
 <mxPoint x="210" y="490" as="sourcePoint"/>
 <mxPoint x="450" y="410" as="targetPoint"/>
 </mxGeometry>
 </mxCell>
  <mxCell id= "322" value= "Fabs Submission" style= "endArrow=classic;whiteSpace=wrap;" source= "248" target= "222" edge="1" parent="1" >
<mxGeometry width="50" height="50" as="geometry">
 <mxPoint x="210" y="490" as="sourcePoint"/>
 <mxPoint x="450" y="410" as="targetPoint"/>
 </mxGeometry>
 </mxCell>
  <mxCell id= "323" value= "User" style= "endArrow=classic;whiteSpace=wrap;" source= "249" target= "216" edge="1" parent="1" >
<mxGeometry width="50" height="50" as="geometry">
 <mxPoint x="210" y="490" as="sourcePoint"/>
 <mxPoint x="450" y="410" as="targetPoint"/>
 </mxGeometry>
 </mxCell>
  <mxCell id= "452" value= "Submission" style= "endArrow=classic;whiteSpace=wrap;" source= "248" target= "224" edge="1" parent="1" >
<mxGeometry width="50" height="50" as="geometry">
 <mxPoint x="210" y="490" as="sourcePoint"/>
 <mxPoint x="450" y="410" as="targetPoint"/>
 </mxGeometry>
 </mxCell>
</root>
</mxGraphModel>
